{
  "cliVersion": "5.73.0",
  "generatorName": "fernapi/fern-csharp-sdk",
  "generatorVersion": "2.65.0",
  "generatorConfig": {
    "namespace": "KardFinancial",
    "client-class-name": "KardClient",
    "exported-client-class-name": "KardClient",
    "environment-class-name": "KardEnvironment",
    "base-api-exception-class-name": "KardApiException",
    "base-exception-class-name": "KardException",
    "generate-mock-server-tests": true
  },
  "originGitCommit": "94416d7da5e82c4836ea191f48265b3ff6c1000f",
  "originGitCommitIsDirty": true,
  "invokedBy": "ci",
  "requestedVersion": "AUTO",
  "ciProvider": "unknown",
  "sdkVersion": "17.0.0"
}