{
  "cliVersion": "5.56.0",
  "generatorName": "fernapi/fern-csharp-sdk",
  "generatorVersion": "2.65.0",
  "generatorConfig": {
    "namespace": "KardFinancial",
    "client-class-name": "KardClient",
    "exported-client-class-name": "KardClient",
    "environment-class-name": "KardEnvironment",
    "base-api-exception-class-name": "KardApiException",
    "base-exception-class-name": "KardException",
    "generate-mock-server-tests": true
  },
  "originGitCommit": "871f1b27ea1980299c8c34470a372966d9ff074e",
  "originGitCommitIsDirty": true,
  "invokedBy": "ci",
  "requestedVersion": "AUTO",
  "ciProvider": "unknown",
  "sdkVersion": "15.1.0"
}